{
  "project_info": {
    "project_number": "553137763211",
    "project_id": "malariatyphoid-a8d08",
    "storage_bucket": "malariatyphoid-a8d08.appspot.com"
  },
  "client": [
    {
      "client_info": {
        "mobilesdk_app_id": "1:553137763211:android:6724e31a739e58521f358e",
        "android_client_info": {
          "package_name": "com.malaria.typhoid"
        }
      },
      "oauth_client": [
        {
          "client_id": "553137763211-4vksqdvhmbv1j2akqto9f9io7ojih8rg.apps.googleusercontent.com",
          "client_type": 3
        }
      ],
      "api_key": [
        {
          "current_key": "AIzaSyC2pC8ctfhVjHSIuZDm_NMk4WsjUnF4fdA"
        }
      ],
      "services": {
        "appinvite_service": {
          "other_platform_oauth_client": [
            {
              "client_id": "553137763211-4vksqdvhmbv1j2akqto9f9io7ojih8rg.apps.googleusercontent.com",
              "client_type": 3
            }
          ]
        }
      }
    }
  ],
  "configuration_version": "1"
}